rdfvr.py
rdfvr-0.3.4.dist-info/METADATA
rdfvr-0.3.4.dist-info/WHEEL
rdfvr-0.3.4.dist-info/entry_points.txt
rdfvr-0.3.4.dist-info/top_level.txt
rdfvr-0.3.4.dist-info/RECORD
