Metadata-Version: 2.1
Name: rdfvr
Version: 0.3.4
Summary: RDFVR: RDF Validation Report
Home-page: https://github.com/meng6/rdfvr
Author: Meng Li
Classifier: Programming Language :: Python :: 3.10
Classifier: Operating System :: OS Independent
Requires-Python: >=3.10
Requires-Dist: pandas >=2.1.0
Requires-Dist: pyshacl >=0.23.0
Requires-Dist: rdflib >=6.3.2
Requires-Dist: pyvis >=0.3.2
Requires-Dist: networkx >=3.3
Provides-Extra: dev
Requires-Dist: pytest >=7.0 ; extra == 'dev'
Requires-Dist: twine >=4.0.2 ; extra == 'dev'
